hello_smr39_rasa/__init__.py
hello_smr39_rasa/gunicorn_conf.py
hello_smr39_rasa/hello.py
hello_smr39_rasa/wsgi.py
hello_smr39_rasa-0.1.8.dist-info/WHEEL
hello_smr39_rasa-0.1.8.dist-info/METADATA
hello_smr39_rasa-0.1.8.dist-info/RECORD
